massedit_cli/__init__.py
massedit_cli-0.1.3.dist-info/entry_points.txt
massedit_cli-0.1.3.dist-info/WHEEL
massedit_cli-0.1.3.dist-info/METADATA
massedit_cli-0.1.3.dist-info/RECORD
