Metadata-Version: 2.1
Name: massedit-cli
Version: 0.1.3
Summary: Python mass editor CLI
Home-page: https://github.com/tddschn/massedit-cli
License: MIT
Keywords: massedit,cli
Author: Xinyuan Chen
Author-email: 45612704+tddschn@users.noreply.github.com
Requires-Python: >=3.10,<4.0
Classifier: License :: OSI Approved :: MIT License
Classifier: Programming Language :: Python :: 3
Classifier: Programming Language :: Python :: 3.10
Classifier: Topic :: Utilities
Requires-Dist: massedit (>=0.69.1,<0.70.0)
Project-URL: Bug Tracker, https://github.com/tddschn/massedit-cli/issues
Project-URL: Repository, https://github.com/tddschn/massedit-cli
